Metadata-Version: 1.1
Name: gec
Version: 0.1.1
Summary: A ECC implementation via oop style abstract algebra
Home-page: UNKNOWN
Author: ryankung
Author-email: ryankung@ieee.org
License: MIT
Platform: any
Classifier: Intended Audience :: Developers
Classifier: Programming Language :: Python
Classifier: Topic :: Software Development :: Libraries :: Python Modules
